README
nosetwilio.py
setup.py
NoseTwilio.egg-info/PKG-INFO
NoseTwilio.egg-info/SOURCES.txt
NoseTwilio.egg-info/dependency_links.txt
NoseTwilio.egg-info/entry_points.txt
NoseTwilio.egg-info/requires.txt
NoseTwilio.egg-info/top_level.txt